Metadata-Version: 2.1
Name: s2froms3
Version: 0.1.0
Summary: Get Sentinel-2 (Cloud Optimized Geotiffs) COG files from AWS S3.
Home-page: https://github.com/kikocorreoso/s2froms3
Author: Kiko Correoso
Author-email: kikocorreoso@example.com
License: MIT
Platform: UNKNOWN
Classifier: License :: OSI Approved :: MIT License
Classifier: Programming Language :: Python
Classifier: Programming Language :: Python :: 3
Classifier: Programming Language :: Python :: 3.7
Classifier: Programming Language :: Python :: 3.8
Classifier: Programming Language :: Python :: Implementation :: CPython
Requires-Python: >=3.7,<3.9
Provides-Extra: tests
